extraneous/__init__.py
extraneous/extraneous.py
extraneous-2.0.5.data/scripts/extraneous.py
extraneous-2.0.5.dist-info/LICENSE
extraneous-2.0.5.dist-info/METADATA
extraneous-2.0.5.dist-info/WHEEL
extraneous-2.0.5.dist-info/top_level.txt
extraneous-2.0.5.dist-info/RECORD
