Metadata-Version: 2.1
Name: extraneous
Version: 2.0.5
Summary: Find extraneous pip packages not listed in your requirements.txt or as a sub-dependency.
Home-page: https://github.com/arrai-innovations/extraneous/
Author: Arrai Innovations
Author-email: support@arrai.com
License: LICENSE
Platform: UNKNOWN
Classifier: Development Status :: 5 - Production/Stable
Classifier: Programming Language :: Python :: 3
Classifier: Programming Language :: Python :: 3.6
Classifier: Programming Language :: Python :: 3.7
Classifier: Programming Language :: Python :: 3.8
Classifier: Programming Language :: Python :: 3.9
Classifier: Programming Language :: Python :: 3.10
Classifier: License :: OSI Approved :: BSD License
Classifier: Environment :: Console
Classifier: Intended Audience :: Developers
Requires-Dist: pipdeptree (<3.0.0,>=2.0.0)
Requires-Dist: ansicolors (<2.0.0,>=1.1.8)
